xmlcord/__init__.py
xmlcord/hooks.py
xmlcord/interface.py
xmlcord/listener.py
xmlcord/renderer.py
xmlcord/safeval.py
xmlcord/utils.py
xmlcord/tags/__init__.py
xmlcord/tags/action.py
xmlcord/tags/ansi.py
xmlcord/tags/base.py
xmlcord/tags/control.py
xmlcord/tags/discord_tags.py
xmlcord/tags/root.py
xmlcord-1.1.2.dist-info/METADATA
xmlcord-1.1.2.dist-info/WHEEL
xmlcord-1.1.2.dist-info/top_level.txt
xmlcord-1.1.2.dist-info/RECORD
