Metadata-Version: 2.1
Name: xmlcord
Version: 1.1.2
Home-page: https://github.com/Fliqqr/xmlcord
Author: Fliqqr
Author-email: author@example.com
Classifier: Programming Language :: Python :: 3
Classifier: License :: OSI Approved :: MIT License
Classifier: Operating System :: OS Independent
Requires-Python: >=3.10
Requires-Dist: aiohttp
Requires-Dist: discord.py>=2.4.0
